ghcr_badge/__init__.py
ghcr_badge/dicts.py
ghcr_badge/generate.py
ghcr_badge/main.py
ghcr_badge/py.typed
ghcr_badge/server.py
ghcr_badge/static/favicon.ico
ghcr_badge/static/favicon.png
ghcr_badge/svg/mark-github.svg
ghcr_badge/svg/package-16.svg
ghcr_badge/templates/index.j2
ghcr_badge-1.0.1.dist-info/METADATA
ghcr_badge-1.0.1.dist-info/WHEEL
ghcr_badge-1.0.1.dist-info/entry_points.txt
ghcr_badge-1.0.1.dist-info/licenses/LICENSE.txt
ghcr_badge-1.0.1.dist-info/RECORD
