Metadata-Version: 2.4
Name: ghcr-badge
Version: 1.0.1
Summary: Generate ghcr.io container's status badge
Project-URL: Repository, https://github.com/eggplants/ghcr-badge
Author-email: eggplants <w10776e8w@yahoo.co.jp>
License: MIT
License-File: LICENSE.txt
Keywords: badge,ghcr,github-container-registry
Classifier: Development Status :: 3 - Alpha
Classifier: License :: OSI Approved :: MIT License
Classifier: Programming Language :: Python :: 3 :: Only
Classifier: Programming Language :: Python :: 3.10
Classifier: Programming Language :: Python :: 3.11
Classifier: Programming Language :: Python :: 3.12
Classifier: Programming Language :: Python :: 3.13
Classifier: Programming Language :: Python :: 3.14
Classifier: Programming Language :: Python :: Implementation :: CPython
Classifier: Typing :: Typed
Requires-Python: <4,>=3.10
Requires-Dist: anybadge<2,>=1.16
Requires-Dist: flask<4,>=3.1
Requires-Dist: gunicorn<24,>=23
Requires-Dist: humanfriendly<11,>=10
Requires-Dist: requests<3,>=2.32.3
Requires-Dist: types-humanfriendly<11,>=10.0.1.20241221
Requires-Dist: types-requests<3,>=2.32.0.20241016
Requires-Dist: types-waitress>=3.0.1.20250801
Requires-Dist: typing-extensions<5,>=4.12.2
Requires-Dist: waitress<4,>=3.0.2
